{
  "彎": {
    "pinyin": "wān",
    "definition": "to bend; bent; a bend; a turn (in a road etc); CL:道[dao4]"
  },
  "彎嘴濱鷸": {
    "pinyin": "wān zuǐ bīn yù",
    "definition": "(bird species of China) curlew sandpiper (Calidris ferruginea)"
  },
  "彎子": {
    "pinyin": "wān zi",
    "definition": "bend; turn; curve"
  },
  "彎彎": {
    "pinyin": "wān wān",
    "definition": "Wan Wan (1981-), Taiwanese blogger and cartoonist"
  },
  "彎彎曲曲": {
    "pinyin": "wān wān qū qū",
    "definition": "curved; meandering; zigzagging"
  },
  "彎折": {
    "pinyin": "wān zhé",
    "definition": "to bend"
  },
  "彎曲": {
    "pinyin": "wān qū",
    "definition": "to bend; to curve around; curved; crooked; to wind; to warp"
  },
  "彎曲度": {
    "pinyin": "wān qǔ dù",
    "definition": "curvature; camber"
  },
  "彎曲空間": {
    "pinyin": "wān qū kōng jiān",
    "definition": "curved space"
  },
  "彎月": {
    "pinyin": "wān yuè",
    "definition": "crescent moon; crescent shape"
  },
  "彎月形透鏡": {
    "pinyin": "wān yuè xíng tòu jìng",
    "definition": "meniscus lens"
  },
  "彎液面": {
    "pinyin": "wān yè miàn",
    "definition": "meniscus (physics)"
  },
  "彎男": {
    "pinyin": "wān nán",
    "definition": "gay guy"
  },
  "彎管麵": {
    "pinyin": "wān guǎn miàn",
    "definition": "elbow pasta"
  },
  "彎腰": {
    "pinyin": "wān yāo",
    "definition": "to stoop"
  },
  "彎腰駝背": {
    "pinyin": "wān yāo tuó bèi",
    "definition": "slouch; stoop; poor posture"
  },
  "彎角": {
    "pinyin": "wān jiǎo",
    "definition": "corner; bend; curve"
  },
  "彎路": {
    "pinyin": "wān lù",
    "definition": "winding road; roundabout route; detour; (fig.) wrong way (of doing sth)"
  },
  "彎道": {
    "pinyin": "wān dào",
    "definition": "winding road; road curve"
  },
  "彎道超車": {
    "pinyin": "wān dào chāo chē",
    "definition": "to overtake on a bend (driving); (fig.) taking opportunity of tight corners to make swift progress (economy etc)"
  }
}