{
  "拘": {
    "pinyin": "jū",
    "definition": "to capture; to restrain; to constrain; to adhere rigidly to; inflexible"
  },
  "拘傳": {
    "pinyin": "jū chuán",
    "definition": "subpoena; to summon (for questioning)"
  },
  "拘囚": {
    "pinyin": "jū qiú",
    "definition": "to imprison; prisoner"
  },
  "拘執": {
    "pinyin": "jū zhí",
    "definition": "rigid; inflexible"
  },
  "拘守": {
    "pinyin": "jū shǒu",
    "definition": "to hold tight; to cling to; to adhere; stubborn; to detain sb as prisoner"
  },
  "拘役": {
    "pinyin": "jū yì",
    "definition": "detention"
  },
  "拘忌": {
    "pinyin": "jū jì",
    "definition": "to have scruples; to have misgivings"
  },
  "拘押": {
    "pinyin": "jū yā",
    "definition": "to arrest; to take into custody"
  },
  "拘押營": {
    "pinyin": "jū yā yíng",
    "definition": "detention center; prison camp"
  },
  "拘拿": {
    "pinyin": "jū ná",
    "definition": "to arrest"
  },
  "拘捕": {
    "pinyin": "jū bǔ",
    "definition": "to arrest"
  },
  "拘攣": {
    "pinyin": "jū luán",
    "definition": "cramps; muscular spasm; fig. constrained; ill at ease"
  },
  "拘攣兒": {
    "pinyin": "jū luán ér",
    "definition": "erhua variant of 拘攣|拘挛[ju1 luan2]"
  },
  "拘束": {
    "pinyin": "jū shù",
    "definition": "to restrict; to restrain; constrained; awkward; ill at ease; uncomfortable; reticent"
  },
  "拘束衣": {
    "pinyin": "jū shù yī",
    "definition": "straightjacket"
  },
  "拘檢": {
    "pinyin": "jū jiǎn",
    "definition": "restrained and cautious"
  },
  "拘泥": {
    "pinyin": "jū nì",
    "definition": "to be a stickler for formalities; to rigidly adhere to; to cling to; constrained; ill at ease"
  },
  "拘牽": {
    "pinyin": "jū qiān",
    "definition": "restrained; confined"
  },
  "拘留": {
    "pinyin": "jū liú",
    "definition": "to detain (a prisoner); to keep sb in custody"
  },
  "拘留所": {
    "pinyin": "jū liú suǒ",
    "definition": "detention center; prison"
  },
  "拘票": {
    "pinyin": "jū piào",
    "definition": "warrant (for arrest)"
  },
  "拘禁": {
    "pinyin": "jū jìn",
    "definition": "constraint; to detain; to take into custody"
  },
  "拘禮": {
    "pinyin": "jū lǐ",
    "definition": "to stand on ceremony; punctilious"
  },
  "拘謹": {
    "pinyin": "jū jǐn",
    "definition": "reserved; overcautious"
  },
  "拘迂": {
    "pinyin": "jū yū",
    "definition": "inflexible; stubborn"
  }
}