{
  "朝": {
    "pinyin": "cháo",
    "definition": "morning"
  },
  "朝三暮四": {
    "pinyin": "zhāo sān mù sì",
    "definition": "lit. say three in the morning but four in the evening (idiom); to change sth that is already settled upon; indecisive; to blow hot and cold"
  },
  "朝不保夕": {
    "pinyin": "zhāo bù bǎo xī",
    "definition": "at dawn, not sure of lasting to evening (idiom); precarious state; imminent crisis; living from hand to mouth"
  },
  "朝不慮夕": {
    "pinyin": "cháo bù lǜ xī",
    "definition": "at dawn, not sure of lasting to evening (idiom); precarious state; imminent crisis; living from hand to mouth"
  },
  "朝中": {
    "pinyin": "cháo zhōng",
    "definition": "North Korea-China"
  },
  "朝中社": {
    "pinyin": "cháo zhōng shè",
    "definition": "abbr. for 朝鮮中央通訊社|朝鲜中央通讯社[Chao2 xian3 Zhong1 yang1 Tong1 xun4 she4]"
  },
  "朝乾夕惕": {
    "pinyin": "zhāo qián xī tì",
    "definition": "cautious and diligent all day long (idiom)"
  },
  "朝代": {
    "pinyin": "cháo dài",
    "definition": "dynasty; reign (of a king)"
  },
  "朝令夕改": {
    "pinyin": "zhāo lìng xī gǎi",
    "definition": "to make frequent or unpredictable changes in policy (idiom)"
  },
  "朝前": {
    "pinyin": "cháo qián",
    "definition": "facing forwards"
  },
  "朝勞動黨": {
    "pinyin": "cháo láo dòng dǎng",
    "definition": "Workers' Party of Korea (WPK), the ruling party of North Korea"
  },
  "朝向": {
    "pinyin": "cháo xiàng",
    "definition": "toward; to face; to open onto; to turn towards; orientation; exposure; Qibla (Islam)"
  },
  "朝夕": {
    "pinyin": "zhāo xī",
    "definition": "morning and night; all the time"
  },
  "朝夕相處": {
    "pinyin": "cháo xī xiāng chù",
    "definition": "to spend all one's time together (idiom)"
  },
  "朝天": {
    "pinyin": "cháo tiān",
    "definition": "to have an audience with the Emperor; to be presented at court; to look skyward; to look up"
  },
  "朝天區": {
    "pinyin": "cháo tiān qū",
    "definition": "Chaotian district of Guangyuan city 廣元市|广元市[Guang3 yuan2 shi4], Sichuan"
  },
  "朝天椒": {
    "pinyin": "cháo tiān jiāo",
    "definition": "chili pepper (Capsicum frutescens var)"
  },
  "朝山進香": {
    "pinyin": "cháo shān jìn xiāng",
    "definition": "to go on a pilgrimage and offer incense (idiom)"
  },
  "朝庭": {
    "pinyin": "cháo tíng",
    "definition": "variant of 朝廷[chao2 ting2]"
  },
  "朝廷": {
    "pinyin": "cháo tíng",
    "definition": "court; imperial household; dynasty"
  },
  "朝後": {
    "pinyin": "cháo hòu",
    "definition": "backwards; facing back"
  },
  "朝思暮想": {
    "pinyin": "zhāo sī mù xiǎng",
    "definition": "to yearn for sth day and night (idiom)"
  },
  "朝戰": {
    "pinyin": "cháo zhàn",
    "definition": "abbr. for 朝鮮戰爭|朝鲜战争[Chao2 xian3 Zhan4 zheng1], Korean War (1950-1953)"
  },
  "朝房": {
    "pinyin": "cháo fáng",
    "definition": "reception room for officials (in former times)"
  },
  "朝拜": {
    "pinyin": "cháo bài",
    "definition": "to worship; to make customary deferences to; a pilgrimage"
  },
  "朝拜聖山": {
    "pinyin": "cháo bài shèng shān",
    "definition": "a pilgrimage to a holy mountain"
  },
  "朝族": {
    "pinyin": "cháo zú",
    "definition": "Korean ethnic group of Jilin province and northeast China; same as 朝鮮族|朝鲜族"
  },
  "朝日": {
    "pinyin": "zhāo rì",
    "definition": "morning sun"
  },
  "朝日新聞": {
    "pinyin": "zhāo rì xīn wén",
    "definition": "Asahi Shimbun (Japanese newspaper)"
  },
  "朝曦": {
    "pinyin": "cháo xī",
    "definition": "early morning sunlight"
  },
  "朝服": {
    "pinyin": "cháo fú",
    "definition": "court dress in former times"
  },
  "朝朝": {
    "pinyin": "cháo cháo",
    "definition": "every day (archaic)"
  },
  "朝朝暮暮": {
    "pinyin": "zhāo zhāo mù mù",
    "definition": "from dawn to dusk; all the time"
  },
  "朝核問題": {
    "pinyin": "cháo hé wèn tí",
    "definition": "Korean nuclear problem"
  },
  "朝歌": {
    "pinyin": "cháo gē",
    "definition": "Zhaoge, capital of the Shang dynasty 商朝; Zhaoge town in Qi county 淇縣|淇县, Hebi 鶴壁|鹤壁, Henan"
  },
  "朝歌鎮": {
    "pinyin": "cháo gē zhèn",
    "definition": "Zhaoge town in Qi county 淇縣|淇县, Hebi 鶴壁|鹤壁, Henan"
  },
  "朝氣": {
    "pinyin": "cháo qì",
    "definition": "vitality; dynamism"
  },
  "朝氣蓬勃": {
    "pinyin": "cháo qì péng bó",
    "definition": "full of youthful energy (idiom); vigorous; energetic; a bright spark"
  },
  "朝永振一郎": {
    "pinyin": "cháo yǒng zhèn yī láng",
    "definition": "TOMONAGA Shin'ichirō (1906-1979), Japanese physicist, 1965 Nobel prize laureate with Richard Feynman and Julian Schwinger"
  },
  "朝珠": {
    "pinyin": "cháo zhū",
    "definition": "court beads (derived from Buddhist prayer beads)"
  },
  "朝生暮死": {
    "pinyin": "zhāo shēng mù sǐ",
    "definition": "lit. born in the morning and dying at dusk (idiom); fig. ephemeral; transient"
  },
  "朝秦暮楚": {
    "pinyin": "zhāo qín mù chǔ",
    "definition": "serve Qin in the morning Chu in the evening (idiom); quick to switch sides"
  },
  "朝綱": {
    "pinyin": "cháo gāng",
    "definition": "laws and discipline of imperial court"
  },
  "朝聖": {
    "pinyin": "cháo shèng",
    "definition": "to make a pilgrimage"
  },
  "朝聖者": {
    "pinyin": "cháo shèng zhě",
    "definition": "pilgrim"
  },
  "朝聞夕改": {
    "pinyin": "cháo wén xī gǎi",
    "definition": "lit. heard in the morning and changed by the evening; to correct an error very quickly (idiom)"
  },
  "朝臣": {
    "pinyin": "cháo chén",
    "definition": "court councilor"
  },
  "朝花夕拾": {
    "pinyin": "cháo huā xī shí",
    "definition": "\"Dawn Blossoms Plucked at Dusk\", a collection of autobiographical essays by Lu Xun 魯迅|鲁迅[Lu3 Xun4]"
  },
  "朝著": {
    "pinyin": "cháo zhù",
    "definition": "towards"
  },
  "朝見": {
    "pinyin": "cháo jiàn",
    "definition": "to have an audience (with the Emperor)"
  },
  "朝覲": {
    "pinyin": "cháo jìn",
    "definition": "to give audience (of emperor); retainers' duty to pay respect to sovereign; hajj (Islam)"
  },
  "朝貢": {
    "pinyin": "cháo gòng",
    "definition": "to present tribute (to the emperor)"
  },
  "朝過夕改": {
    "pinyin": "cháo guò xī gǎi",
    "definition": "to correct in the evening a fault of the morning (idiom); to quickly amend one's ways"
  },
  "朝野": {
    "pinyin": "cháo yě",
    "definition": "all levels of society; the imperial court and the ordinary people"
  },
  "朝門": {
    "pinyin": "cháo mén",
    "definition": "entrance portal (to a palace); propylaeum"
  },
  "朝陽": {
    "pinyin": "cháo yáng",
    "definition": "the morning sun"
  },
  "朝陽區": {
    "pinyin": "cháo yáng qū",
    "definition": "Chaoyang, an inner district of Beijing; Chaoyang, a district of Changchun City 長春市|长春市[Chang2chun1 Shi4], Jilin; Chaoyang, a district of Shantou City 汕頭市|汕头市[Shan4tou2 Shi4], Guangdong"
  },
  "朝陽市": {
    "pinyin": "cháo yáng shì",
    "definition": "Chaoyang, prefecture-level city in Liaoning Province 遼寧省|辽宁省[Liao2ning2 Sheng3]"
  },
  "朝陽產業": {
    "pinyin": "cháo yáng chǎn yè",
    "definition": "sunrise industry"
  },
  "朝陽縣": {
    "pinyin": "cháo yáng xiàn",
    "definition": "Chaoyang, a county in Chaoyang City 朝陽市|朝阳市[Chao2yang2 Shi4], Liaoning"
  },
  "朝陽門": {
    "pinyin": "cháo yáng mén",
    "definition": "Chaoyangmen neighborhood of Beijing"
  },
  "朝雨": {
    "pinyin": "cháo yǔ",
    "definition": "morning rain"
  },
  "朝露": {
    "pinyin": "zhāo lù",
    "definition": "morning dew; fig. precarious brevity of human life; ephemeral"
  },
  "朝露暮靄": {
    "pinyin": "zhāo lù mù ǎi",
    "definition": "morning dew, evening mist (idiom); ephemeral; impermanent"
  },
  "朝露溘至": {
    "pinyin": "zhāo lù kè zhì",
    "definition": "the morning dew will swiftly dissipate (idiom); fig. ephemeral and precarious nature of human existence"
  },
  "朝韓": {
    "pinyin": "cháo hán",
    "definition": "North and South Korea"
  },
  "朝饔夕飧": {
    "pinyin": "zhāo yōng xī sūn",
    "definition": "lit. breakfast in the morning and supper in the evening (idiom); fig. to do nothing but eat and drink"
  },
  "朝鮮": {
    "pinyin": "cháo xiān",
    "definition": "North Korea; Korea as geographic term; Taiwan pr. [Chao2 xian1]"
  },
  "朝鮮中央通訊社": {
    "pinyin": "cháo xiān zhōng yāng tōng xùn shè",
    "definition": "North Korean Central News Agency (KCNA); abbr. to 朝中社[Chao2 zhong1 she4]"
  },
  "朝鮮人": {
    "pinyin": "cháo xiān rén",
    "definition": "North Korean (person)"
  },
  "朝鮮八道": {
    "pinyin": "cháo xiān bā dào",
    "definition": "the eight provinces of Yi dynasty Korea"
  },
  "朝鮮勞動黨": {
    "pinyin": "cháo xiān láo dòng dǎng",
    "definition": "Workers' Party of Korea (WPK), the ruling party of North Korea"
  },
  "朝鮮半島": {
    "pinyin": "cháo xiān bàn dǎo",
    "definition": "Korean Peninsula"
  },
  "朝鮮太宗": {
    "pinyin": "cháo xiān tài zōng",
    "definition": "King Taejong of Joseon Korea (1367-1422), reigned 1400-1418"
  },
  "朝鮮字母": {
    "pinyin": "cháo xiān zì mǔ",
    "definition": "hangul, Korean phonetic alphabet; Korean letters"
  },
  "朝鮮戰爭": {
    "pinyin": "cháo xiān zhàn zhēng",
    "definition": "Korean War (1950-1953)"
  },
  "朝鮮文": {
    "pinyin": "cháo xiān wén",
    "definition": "Korean written language"
  },
  "朝鮮族": {
    "pinyin": "cháo xiān zú",
    "definition": "Korean ethnic group in China (mainly in northeast China); the Koreans (major ethnic group on the Korean Peninsula)"
  },
  "朝鮮日報": {
    "pinyin": "cháo xiān rì bào",
    "definition": "Chosun Ilbo, a South Korean newspaper"
  },
  "朝鮮核談": {
    "pinyin": "cháo xiān hé tán",
    "definition": "talks on North Korea's nuclear program"
  },
  "朝鮮民主主義人民共和國": {
    "pinyin": "cháo xiān mín zhǔ zhǔ yì rén mín gòng hé guó",
    "definition": "People's Democratic Republic of Korea (North Korea)"
  },
  "朝鮮海峽": {
    "pinyin": "cháo xiān hǎi xiá",
    "definition": "Korea Strait; Tsushima Strait (between Japan and Korea)"
  },
  "朝鮮箏": {
    "pinyin": "cháo xiān zhēng",
    "definition": "gayageum (Korean 12-stringed zither)"
  },
  "朝鮮總督府": {
    "pinyin": "cháo xiān zǒng dū fǔ",
    "definition": "Japanese colonial administration of Korea 1910-1945"
  },
  "朝鮮語": {
    "pinyin": "cháo xiān yǔ",
    "definition": "Korean language"
  }
}