{
  "產": {
    "pinyin": "chǎn",
    "definition": "to give birth; to reproduce; to produce; product; resource; estate; property"
  },
  "產下": {
    "pinyin": "chǎn xià",
    "definition": "to bear (give birth)"
  },
  "產仔": {
    "pinyin": "chǎn zǎi",
    "definition": "to give birth (animals); to bear a litter"
  },
  "產值": {
    "pinyin": "chǎn zhí",
    "definition": "value of output; output value"
  },
  "產假": {
    "pinyin": "chǎn jiǎ",
    "definition": "maternity leave"
  },
  "產兒": {
    "pinyin": "chǎn ér",
    "definition": "newborn baby; fig. brand-new object"
  },
  "產出": {
    "pinyin": "chǎn chū",
    "definition": "to produce (graduates, breast milk, toxic waste, creative ideas etc); output"
  },
  "產前": {
    "pinyin": "chǎn qián",
    "definition": "prenatal; antenatal"
  },
  "產前檢查": {
    "pinyin": "chǎn qián jiǎn chá",
    "definition": "prenatal checkup; antenatal examination"
  },
  "產區": {
    "pinyin": "chǎn qū",
    "definition": "place of production; manufacturing location"
  },
  "產卵": {
    "pinyin": "chǎn luǎn",
    "definition": "to lay eggs"
  },
  "產品": {
    "pinyin": "chǎn pǐn",
    "definition": "goods; merchandise; product; CL:個|个[ge4]"
  },
  "產品結構": {
    "pinyin": "chǎn pǐn jié gòu",
    "definition": "product mix"
  },
  "產品經理": {
    "pinyin": "chǎn pǐn jīng lǐ",
    "definition": "product manager"
  },
  "產地": {
    "pinyin": "chǎn dì",
    "definition": "source (of a product); place of origin; manufacturing location"
  },
  "產地證": {
    "pinyin": "chǎn dì zhèng",
    "definition": "certificate of origin (CO or CoO) (commerce)"
  },
  "產婆": {
    "pinyin": "chǎn pó",
    "definition": "midwife"
  },
  "產婦": {
    "pinyin": "chǎn fù",
    "definition": "woman recuperating after childbirth; woman in childbirth"
  },
  "產後": {
    "pinyin": "chǎn hòu",
    "definition": "postnatal"
  },
  "產房": {
    "pinyin": "chǎn fáng",
    "definition": "delivery room (in hospital); labor ward"
  },
  "產期": {
    "pinyin": "chǎn qī",
    "definition": "time of birth; period of labor; lying-in"
  },
  "產業": {
    "pinyin": "chǎn yè",
    "definition": "industry; estate; property; industrial"
  },
  "產業化": {
    "pinyin": "chǎn yè huà",
    "definition": "to industrialize; industrialization"
  },
  "產業工人": {
    "pinyin": "chǎn yè gōng rén",
    "definition": "industrial worker"
  },
  "產業鏈": {
    "pinyin": "chǎn yè liàn",
    "definition": "industry value chain"
  },
  "產業集群": {
    "pinyin": "chǎn yè jí qún",
    "definition": "industrial cluster"
  },
  "產檢": {
    "pinyin": "chǎn jiǎn",
    "definition": "prenatal checkup (abbr. for 產前檢查|产前检查[chan3 qian2 jian3 cha2])"
  },
  "產權": {
    "pinyin": "chǎn quán",
    "definition": "property right"
  },
  "產油國": {
    "pinyin": "chǎn yóu guó",
    "definition": "oil-producing countries"
  },
  "產物": {
    "pinyin": "chǎn wù",
    "definition": "product; result (of)"
  },
  "產生": {
    "pinyin": "chǎn shēng",
    "definition": "to arise; to come into being; to come about; to give rise to; to bring into being; to bring about; to produce; to engender; to generate"
  },
  "產科": {
    "pinyin": "chǎn kē",
    "definition": "maternity department; maternity ward; obstetrics"
  },
  "產程": {
    "pinyin": "chǎn chéng",
    "definition": "the process of childbirth"
  },
  "產糧": {
    "pinyin": "chǎn liáng",
    "definition": "to grow crops; food growing"
  },
  "產糧區": {
    "pinyin": "chǎn liáng qū",
    "definition": "food growing area"
  },
  "產糧大省": {
    "pinyin": "chǎn liáng dà shěng",
    "definition": "major agricultural province"
  },
  "產經新聞": {
    "pinyin": "chǎn jīng xīn wén",
    "definition": "Business News; Sankei Shimbun (Tokyo daily)"
  },
  "產線": {
    "pinyin": "chǎn xiàn",
    "definition": "production line"
  },
  "產能": {
    "pinyin": "chǎn néng",
    "definition": "production capacity"
  },
  "產製": {
    "pinyin": "chǎn zhì",
    "definition": "production; manufacture"
  },
  "產褥期": {
    "pinyin": "chǎn rù qī",
    "definition": "postnatal period; puerperium (period of six weeks after childbirth)"
  },
  "產褥熱": {
    "pinyin": "chǎn rù rè",
    "definition": "postnatal fever; puerperal fever; childbed fever"
  },
  "產道": {
    "pinyin": "chǎn dào",
    "definition": "birth canal (in obstetrics)"
  },
  "產量": {
    "pinyin": "chǎn liàng",
    "definition": "output"
  },
  "產鉗": {
    "pinyin": "chǎn qián",
    "definition": "obstetric forceps"
  },
  "產銷": {
    "pinyin": "chǎn xiāo",
    "definition": "production and sales; production and marketing"
  },
  "產院": {
    "pinyin": "chǎn yuàn",
    "definition": "maternity hospital"
  },
  "產露": {
    "pinyin": "chǎn lù",
    "definition": "(Tw) (medicine) lochia"
  }
}