{
  "視": {
    "pinyin": "shì",
    "definition": "(literary, or bound form) to look at"
  },
  "視乎": {
    "pinyin": "shì hū",
    "definition": "to be determined by; to depend on"
  },
  "視亮度": {
    "pinyin": "shì liàng dù",
    "definition": "apparent brightness (astronomy)"
  },
  "視作": {
    "pinyin": "shì zuò",
    "definition": "to regard as; to treat as"
  },
  "視像": {
    "pinyin": "shì xiàng",
    "definition": "video (HK)"
  },
  "視力": {
    "pinyin": "shì lì",
    "definition": "vision; eyesight"
  },
  "視力測定法": {
    "pinyin": "shì lì cè dìng fǎ",
    "definition": "optometry; eyesight testing"
  },
  "視力表": {
    "pinyin": "shì lì biǎo",
    "definition": "eye chart (used by optician)"
  },
  "視區": {
    "pinyin": "shì qū",
    "definition": "field of view"
  },
  "視同": {
    "pinyin": "shì tóng",
    "definition": "to regard the same as; to regard as being the same as"
  },
  "視同兒戲": {
    "pinyin": "shì tóng ér xì",
    "definition": "to regard sth as a plaything (idiom); to consider unimportant; to view as trifling"
  },
  "視同己出": {
    "pinyin": "shì tóng jǐ chū",
    "definition": "to regard sb as one's own child"
  },
  "視同手足": {
    "pinyin": "shì tóng shǒu zú",
    "definition": "to regard sb as a brother (idiom)"
  },
  "視圖": {
    "pinyin": "shì tú",
    "definition": "view"
  },
  "視如土芥": {
    "pinyin": "shì rú tǔ jiè",
    "definition": "to regard as useless; to view as no better than weeds"
  },
  "視如寇仇": {
    "pinyin": "shì rú kòu chóu",
    "definition": "to regard as an enemy"
  },
  "視如敝屣": {
    "pinyin": "shì rú bì xǐ",
    "definition": "lit. to view as worn-out shoes (idiom); fig. to consider to be worthless"
  },
  "視如糞土": {
    "pinyin": "shì rú fèn tǔ",
    "definition": "to look upon as dirt; considered worthless"
  },
  "視姦": {
    "pinyin": "shì jiān",
    "definition": "(neologism) to obsessively monitor sb's social media posts (orthographic borrowing from Japanese 視姦 \"shikan\", ogling; leering)"
  },
  "視察": {
    "pinyin": "shì chá",
    "definition": "to inspect; an investigation"
  },
  "視屏": {
    "pinyin": "shì píng",
    "definition": "screen (of a TV, computer etc)"
  },
  "視差": {
    "pinyin": "shì chà",
    "definition": "parallax"
  },
  "視微知著": {
    "pinyin": "shì wēi zhī zhù",
    "definition": "see 見微知著|见微知著[jian4wei1-zhi1zhu4]"
  },
  "視損傷": {
    "pinyin": "shì sǔn shāng",
    "definition": "visual impairment"
  },
  "視效": {
    "pinyin": "shì xiào",
    "definition": "visual effect (abbr. for 視覺效果|视觉效果[shi4jue2 xiao4guo3])"
  },
  "視死如歸": {
    "pinyin": "shì sǐ rú guī",
    "definition": "to view death as a return home; to not be afraid of dying; to face death with equanimity (idiom)"
  },
  "視為": {
    "pinyin": "shì wèi",
    "definition": "to view as; to see as; to consider to be; to deem"
  },
  "視為畏途": {
    "pinyin": "shì wèi wèi tú",
    "definition": "to view as dangerous (idiom); afraid to do sth"
  },
  "視為知己": {
    "pinyin": "shì wèi zhī jǐ",
    "definition": "to consider sb as close friend (idiom); to take into one's confidence"
  },
  "視界": {
    "pinyin": "shì jiè",
    "definition": "field of vision"
  },
  "視盤": {
    "pinyin": "shì pán",
    "definition": "optic disc (anatomy); video compact disc (VCD)"
  },
  "視盲": {
    "pinyin": "shì máng",
    "definition": "blindness"
  },
  "視神經": {
    "pinyin": "shì shén jīng",
    "definition": "optic nerve"
  },
  "視神經乳頭": {
    "pinyin": "shì shén jīng rǔ tóu",
    "definition": "optic disk (terminal of the optic nerve on the retina)"
  },
  "視神經盤": {
    "pinyin": "shì shén jīng pán",
    "definition": "optic disk (terminal of the optic nerve on the retina)"
  },
  "視窗": {
    "pinyin": "shì chuāng",
    "definition": "a window (on a computer screen)"
  },
  "視網膜": {
    "pinyin": "shì wǎng mó",
    "definition": "retina"
  },
  "視線": {
    "pinyin": "shì xiàn",
    "definition": "line of sight"
  },
  "視而不見": {
    "pinyin": "shì ér bù jiàn",
    "definition": "(idiom) to turn a blind eye to; to ignore"
  },
  "視聽材料": {
    "pinyin": "shì tīng cái liào",
    "definition": "evidence of material seen and heard; oral testimony"
  },
  "視若無睹": {
    "pinyin": "shì ruò wú dǔ",
    "definition": "to turn a blind eye to"
  },
  "視若路人": {
    "pinyin": "shì ruò lù rén",
    "definition": "to view as strangers"
  },
  "視藝": {
    "pinyin": "shì yì",
    "definition": "visual arts"
  },
  "視覺": {
    "pinyin": "shì jué",
    "definition": "sight; vision; visual"
  },
  "視覺方言": {
    "pinyin": "shì jué fāng yán",
    "definition": "(linguistics) eye dialect"
  },
  "視角": {
    "pinyin": "shì jiǎo",
    "definition": "angle from which one observes an object; (fig.) perspective; viewpoint; frame of reference; (cinematography) camera angle; (visual perception) visual angle (the angle a viewed object subtends at the eye); (photography) angle of view"
  },
  "視訊": {
    "pinyin": "shì xùn",
    "definition": "video (Tw)"
  },
  "視距": {
    "pinyin": "shì jù",
    "definition": "visible range"
  },
  "視野": {
    "pinyin": "shì yě",
    "definition": "field of view; (fig.) outlook; perspective"
  },
  "視錯覺": {
    "pinyin": "shì cuò jué",
    "definition": "optical illusion"
  },
  "視障": {
    "pinyin": "shì zhàng",
    "definition": "visual impairment"
  },
  "視頻": {
    "pinyin": "shì pín",
    "definition": "video"
  },
  "視頻會議": {
    "pinyin": "shì pín huì yì",
    "definition": "videoconferencing; videoconference"
  },
  "視頻節目": {
    "pinyin": "shì pín jié mù",
    "definition": "video program"
  },
  "視頻點播": {
    "pinyin": "shì pín diǎn bō",
    "definition": "video on demand"
  }
}