{
  "覆": {
    "pinyin": "fù",
    "definition": "to cover; to overflow; to overturn; to capsize"
  },
  "覆亡": {
    "pinyin": "fù wáng",
    "definition": "fall (of an empire)"
  },
  "覆巢之下無完卵": {
    "pinyin": "fù cháo zhī xià wú wán luǎn",
    "definition": "lit. when the nest is upset no egg is left intact (idiom); fig. when one falls in disgrace the whole family is doomed"
  },
  "覆巢無完卵": {
    "pinyin": "fù cháo wú wán luǎn",
    "definition": "lit. when the nest overturns no egg remains intact; no member escapes unscathed from a family disaster (idiom)"
  },
  "覆核": {
    "pinyin": "fù hé",
    "definition": "to review; to reexamine; review"
  },
  "覆水難收": {
    "pinyin": "fù shuǐ nán shōu",
    "definition": "spilt water is difficult to retrieve (idiom); it's no use crying over spilt milk; what's done is done and can't be reversed; the damage is done; once divorced, there's no reuniting"
  },
  "覆沒": {
    "pinyin": "fù méi",
    "definition": "annihilated; capsized"
  },
  "覆滅": {
    "pinyin": "fù miè",
    "definition": "destruction"
  },
  "覆疊": {
    "pinyin": "fù dié",
    "definition": "to overlap; to overlay; cascaded (thermodynamic cycle)"
  },
  "覆盆子": {
    "pinyin": "fù pén zi",
    "definition": "raspberry"
  },
  "覆膜": {
    "pinyin": "fù mó",
    "definition": "membrane covering sth; coating"
  },
  "覆蓋": {
    "pinyin": "fù gài",
    "definition": "to cover"
  },
  "覆蓋物": {
    "pinyin": "fù gài wù",
    "definition": "mulch"
  },
  "覆蓋率": {
    "pinyin": "fù gài lǜ",
    "definition": "coverage"
  },
  "覆蓋面": {
    "pinyin": "fù gài miàn",
    "definition": "coverage"
  },
  "覆轍": {
    "pinyin": "fù zhé",
    "definition": "the tracks of a cart that overturned; (fig.) a path that led to failure in the past"
  },
  "覆迭": {
    "pinyin": "fù dié",
    "definition": "variant of 覆疊|覆叠[fu4 die2]"
  },
  "覆述": {
    "pinyin": "fù shù",
    "definition": "variant of 複述|复述[fu4 shu4]"
  }
}