{
  "腫": {
    "pinyin": "zhǒng",
    "definition": "to swell; swelling; swollen"
  },
  "腫塊": {
    "pinyin": "zhǒng kuài",
    "definition": "swelling; growth; tumor; lump"
  },
  "腫大": {
    "pinyin": "zhǒng dà",
    "definition": "swelling; enlargement; hypertrophy"
  },
  "腫瘤": {
    "pinyin": "zhǒng liú",
    "definition": "tumor"
  },
  "腫瘤切除術": {
    "pinyin": "zhǒng liú qiē chú shù",
    "definition": "lumpectomy"
  },
  "腫瘤學": {
    "pinyin": "zhǒng liú xué",
    "definition": "oncology; study of tumors"
  },
  "腫瘤病醫生": {
    "pinyin": "zhǒng liú bìng yī shēng",
    "definition": "oncologist (medicine)"
  },
  "腫脹": {
    "pinyin": "zhǒng zhàng",
    "definition": "swelling; oedema; internal bruising"
  },
  "腫麼": {
    "pinyin": "zhǒng me",
    "definition": "Internet slang for 怎麼|怎么[zen3 me5]"
  }
}