{
  "飼": {
    "pinyin": "sì",
    "definition": "to raise; to rear; to feed"
  },
  "飼料": {
    "pinyin": "sì liào",
    "definition": "feed; fodder"
  },
  "飼槽": {
    "pinyin": "sì cáo",
    "definition": "feeding trough"
  },
  "飼育": {
    "pinyin": "sì yù",
    "definition": "to rear (an animal)"
  },
  "飼草": {
    "pinyin": "sì cǎo",
    "definition": "forage grass"
  },
  "飼養": {
    "pinyin": "sì yǎng",
    "definition": "to raise; to rear"
  },
  "飼養員": {
    "pinyin": "sì yǎng yuán",
    "definition": "zookeeper; stockman; breeder (of livestock, dogs or poultry etc)"
  },
  "飼養場": {
    "pinyin": "sì yǎng chǎng",
    "definition": "farm; feed lot; dry lot"
  },
  "飼養業": {
    "pinyin": "sì yǎng yè",
    "definition": "stock farming; animal husbandry"
  },
  "飼養者": {
    "pinyin": "sì yǎng zhě",
    "definition": "feeder"
  }
}