{
  "交": {
    "pinyin": "jiao1",
    "definition": "to hand over; to deliver; to pay (money); to turn over; to make friends; (of lines) to intersect; variant of 跤[jiao1]"
  },
  "交九": {
    "pinyin": "jiao1 jiu3",
    "definition": "the coldest period of the year; three nine day periods after the winter solstice"
  },
  "交互": {
    "pinyin": "jiao1 hu4",
    "definition": "mutual; interactive; each other; alternately; in turn; interaction"
  },
  "交付": {
    "pinyin": "jiao1 fu4",
    "definition": "to hand over; to deliver"
  },
  "交代": {
    "pinyin": "jiao1 dai4",
    "definition": "to transfer (duties to sb else); to give instructions; to tell (sb to do sth); to explain; to give an account; to brief; to confess; to account for oneself; (jocular) to come to a bad end"
  },
  "交併": {
    "pinyin": "jiao1 bing4",
    "definition": "occurring simultaneously"
  },
  "交保": {
    "pinyin": "jiao1 bao3",
    "definition": "to post bail; bail"
  },
  "交保釋放": {
    "pinyin": "jiao1 bao3 shi4 fang4",
    "definition": "to release sb on bail"
  },
  "交兵": {
    "pinyin": "jiao1 bing1",
    "definition": "in a state of war"
  },
  "交出": {
    "pinyin": "jiao1 chu1",
    "definition": "to hand over"
  },
  "交割": {
    "pinyin": "jiao1 ge1",
    "definition": "delivery (commerce)"
  },
  "交加": {
    "pinyin": "jiao1 jia1",
    "definition": "(of two or more things) to occur at the same time; to be mingled; to accompany each other"
  },
  "交匯": {
    "pinyin": "jiao1 hui4",
    "definition": "to flow together; confluence (of rivers, airflow, roads); (international) cooperation"
  },
  "交匯處": {
    "pinyin": "jiao1 hui4 chu4",
    "definition": "confluence (of two rivers); junction (of roads); (transport) interchange"
  },
  "交卷": {
    "pinyin": "jiao1 juan4",
    "definition": "to hand in one's examination script"
  },
  "交卸": {
    "pinyin": "jiao1 xie4",
    "definition": "to hand over to a successor; to relinquish one's office"
  },
  "交叉": {
    "pinyin": "jiao1 cha1",
    "definition": "to cross; to intersect; to overlap"
  },
  "交叉口": {
    "pinyin": "jiao1 cha1 kou3",
    "definition": "(road) intersection"
  },
  "交叉學科": {
    "pinyin": "jiao1 cha1 xue2 ke1",
    "definition": "interdisciplinary; interdisciplinary subject (in science)"
  },
  "交叉引用": {
    "pinyin": "jiao1 cha1 yin3 yong4",
    "definition": "cross-reference (in a document, index etc)"
  },
  "交叉感染": {
    "pinyin": "jiao1 cha1 gan3 ran3",
    "definition": "cross-infection"
  },
  "交叉火力": {
    "pinyin": "jiao1 cha1 huo3 li4",
    "definition": "crossfire"
  },
  "交叉熵": {
    "pinyin": "jiao1 cha1 shang1",
    "definition": "cross entropy (information theory)"
  },
  "交叉編譯器": {
    "pinyin": "jiao1 cha1 bian1 yi4 qi4",
    "definition": "(computing) cross-compiler"
  },
  "交叉耐藥性": {
    "pinyin": "jiao1 cha1 nai4 yao4 xing4",
    "definition": "cross-tolerance"
  },
  "交叉運球": {
    "pinyin": "jiao1 cha1 yun4 qiu2",
    "definition": "crossover dribble (basketball)"
  },
  "交叉陰影線": {
    "pinyin": "jiao1 cha1 yin1 ying3 xian4",
    "definition": "hatched lines; cross-hatched graphic pattern"
  },
  "交叉點": {
    "pinyin": "jiao1 cha1 dian3",
    "definition": "junction; crossroads; (geometry) point of intersection"
  },
  "交友": {
    "pinyin": "jiao1 you3",
    "definition": "to make friends"
  },
  "交口": {
    "pinyin": "Jiao1 kou3",
    "definition": "Jiaokou county in Lüliang 呂梁|吕梁[Lu:3 liang2], Shanxi 山西"
  },
  "交口稱譽": {
    "pinyin": "jiao1 kou3 cheng1 yu4",
    "definition": "voices unanimous in praise (idiom); with an extensive public reputation"
  },
  "交口縣": {
    "pinyin": "Jiao1 kou3 xian4",
    "definition": "Jiaokou county in Lüliang 呂梁|吕梁[Lu:3 liang2], Shanxi 山西"
  },
  "交合": {
    "pinyin": "jiao1 he2",
    "definition": "to join; to meet; to copulate; sexual intercourse"
  },
  "交售": {
    "pinyin": "jiao1 shou4",
    "definition": "(of a farmer) to sell one's produce to the state as stipulated by government policy"
  },
  "交困": {
    "pinyin": "jiao1 kun4",
    "definition": "beset with difficulties"
  },
  "交城": {
    "pinyin": "Jiao1 cheng2",
    "definition": "Jiaocheng county in Lüliang 呂梁|吕梁[Lu:3 liang2], Shanxi 山西"
  },
  "交城縣": {
    "pinyin": "Jiao1 cheng2 xian4",
    "definition": "Jiaocheng county in Lüliang 呂梁|吕梁[Lu:3 liang2], Shanxi 山西"
  },
  "交大": {
    "pinyin": "Jiao1 da4",
    "definition": "Jiaotong University; University of Communications; abbr. of 交通大學|交通大学[Jiao1 tong1 Da4 xue2]"
  },
  "交契": {
    "pinyin": "jiao1 qi4",
    "definition": "friendship"
  },
  "交好": {
    "pinyin": "jiao1 hao3",
    "definition": "to be on friendly terms"
  },
  "交媾": {
    "pinyin": "jiao1 gou4",
    "definition": "to have sex; to copulate"
  },
  "交安": {
    "pinyin": "jiao1 an1",
    "definition": "road traffic safety (abbr. for 交通安全)"
  },
  "交尾": {
    "pinyin": "jiao1 wei3",
    "definition": "to copulate (of animals); to mate"
  },
  "交差": {
    "pinyin": "jiao1 chai1",
    "definition": "to report back after completion of one's mission"
  },
  "交帳": {
    "pinyin": "jiao1 zhang4",
    "definition": "to settle accounts"
  },
  "交底": {
    "pinyin": "jiao1 di3",
    "definition": "to fill sb in (on the details of sth); to put all one's cards on the table"
  },
  "交強險": {
    "pinyin": "jiao1 qiang2 xian3",
    "definition": "compulsory vehicle insurance (abbr. for 機動車交通事故責任強制保險|机动车交通事故责任强制保险[ji1 dong4 che1 jiao1 tong1 shi4 gu4 ze2 ren4 qiang2 zhi4 bao3 xian3])"
  },
  "交彙": {
    "pinyin": "jiao1 hui4",
    "definition": "variant of 交匯|交汇; to flow together; confluence (of rivers, airflow, roads); (international) cooperation"
  },
  "交往": {
    "pinyin": "jiao1 wang3",
    "definition": "to associate (with); to have contact (with); to hang out (with); to date; (interpersonal) relationship; association; contact"
  },
  "交待": {
    "pinyin": "jiao1 dai4",
    "definition": "variant of 交代[jiao1 dai4]"
  },
  "交心": {
    "pinyin": "jiao1 xin1",
    "definition": "to open one's heart; to have a heart-to-heart conversation"
  },
  "交情": {
    "pinyin": "jiao1 qing5",
    "definition": "friendship; friendly relations"
  },
  "交情匪淺": {
    "pinyin": "jiao1 qing2 fei3 qian3",
    "definition": "to be very close; to understand each other"
  },
  "交惡": {
    "pinyin": "jiao1 wu4",
    "definition": "to become enemies; to become hostile towards each other"
  },
  "交感神經": {
    "pinyin": "jiao1 gan3 shen2 jing1",
    "definition": "sympathetic nervous system"
  },
  "交戰": {
    "pinyin": "jiao1 zhan4",
    "definition": "to fight; to wage war"
  },
  "交手": {
    "pinyin": "jiao1 shou3",
    "definition": "to fight hand to hand"
  },
  "交托": {
    "pinyin": "jiao1 tuo1",
    "definition": "to entrust"
  },
  "交拜": {
    "pinyin": "jiao1 bai4",
    "definition": "to bow to one another; to kneel and kowtow to one another; formal kowtow as part of traditional wedding ceremony"
  },
  "交接": {
    "pinyin": "jiao1 jie1",
    "definition": "(of two things) to come into contact; to meet; to hand over to; to take over from; to associate with; to have friendly relations with; to have sexual intercourse"
  },
  "交接班": {
    "pinyin": "jiao1 jie1 ban1",
    "definition": "to change shift"
  },
  "交換": {
    "pinyin": "jiao1 huan4",
    "definition": "to exchange; to swap; to switch (telecom); commutative (math); to commute"
  },
  "交換代數": {
    "pinyin": "jiao1 huan4 dai4 shu4",
    "definition": "(math.) commutative algebra"
  },
  "交換代數學": {
    "pinyin": "jiao1 huan4 dai4 shu4 xue2",
    "definition": "(math.) commutative algebra"
  },
  "交換以太網絡": {
    "pinyin": "jiao1 huan4 yi3 tai4 wang3 luo4",
    "definition": "switched Ethernet"
  },
  "交換價值": {
    "pinyin": "jiao1 huan4 jia4 zhi2",
    "definition": "exchange value"
  },
  "交換器": {
    "pinyin": "jiao1 huan4 qi4",
    "definition": "(telecom or network) switch"
  },
  "交換律": {
    "pinyin": "jiao1 huan4 lu:4",
    "definition": "commutative law xy = yx (math)"
  },
  "交換技術": {
    "pinyin": "jiao1 huan4 ji4 shu4",
    "definition": "switching technology"
  },
  "交換機": {
    "pinyin": "jiao1 huan4 ji1",
    "definition": "switch (telecommunications)"
  },
  "交換生": {
    "pinyin": "jiao1 huan4 sheng1",
    "definition": "exchange student"
  },
  "交換碼": {
    "pinyin": "jiao1 huan4 ma3",
    "definition": "interchange code; computer coding for characters, including Chinese"
  },
  "交換網路": {
    "pinyin": "jiao1 huan4 wang3 lu4",
    "definition": "switched network"
  },
  "交換虛電路": {
    "pinyin": "jiao1 huan4 xu1 dian4 lu4",
    "definition": "Switched Virtual Circuit; SVC"
  },
  "交易": {
    "pinyin": "jiao1 yi4",
    "definition": "to deal; to trade; to transact; transaction; deal; CL:筆|笔[bi3]"
  },
  "交易員": {
    "pinyin": "jiao1 yi4 yuan2",
    "definition": "dealer; trader"
  },
  "交易市場": {
    "pinyin": "jiao1 yi4 shi4 chang3",
    "definition": "exchange; trading floor"
  },
  "交易所": {
    "pinyin": "jiao1 yi4 suo3",
    "definition": "exchange; stock exchange"
  },
  "交易所交易基金": {
    "pinyin": "jiao1 yi4 suo3 - jiao1 yi4 ji1 jin1",
    "definition": "exchange-traded fund (ETF)"
  },
  "交易日": {
    "pinyin": "jiao1 yi4 ri4",
    "definition": "(finance) trading day"
  },
  "交易會": {
    "pinyin": "jiao1 yi4 hui4",
    "definition": "trade fair"
  },
  "交易者": {
    "pinyin": "jiao1 yi4 zhe3",
    "definition": "dealer"
  },
  "交易額": {
    "pinyin": "jiao1 yi4 e2",
    "definition": "sum or volume of business transactions; turnover"
  },
  "交替": {
    "pinyin": "jiao1 ti4",
    "definition": "to replace; alternately; in turn"
  },
  "交會": {
    "pinyin": "jiao1 hui4",
    "definition": "to encounter; to rendezvous; to converge; to meet (a payment)"
  },
  "交朋友": {
    "pinyin": "jiao1 peng2 you5",
    "definition": "to make friends; (dialect) to start an affair with sb"
  },
  "交杯酒": {
    "pinyin": "jiao1 bei1 jiu3",
    "definition": "formal exchange of cups of wine between bride and groom as traditional wedding ceremony"
  },
  "交椅": {
    "pinyin": "jiao1 yi3",
    "definition": "old-style wooden folding armchair, typically featuring a footrest; (fig.) position in a hierarchy"
  },
  "交款單": {
    "pinyin": "jiao1 kuan3 dan1",
    "definition": "payment slip"
  },
  "交歡": {
    "pinyin": "jiao1 huan1",
    "definition": "to have cordial relations with each other; to have sexual intercourse"
  },
  "交流": {
    "pinyin": "jiao1 liu2",
    "definition": "to exchange; exchange; communication; interaction; to have social contact (with sb)"
  },
  "交流道": {
    "pinyin": "jiao1 liu2 dao4",
    "definition": "(Tw) highway interchange; (fig.) channel of communication"
  },
  "交流電": {
    "pinyin": "jiao1 liu2 dian4",
    "definition": "alternating current"
  },
  "交涉": {
    "pinyin": "jiao1 she4",
    "definition": "to negotiate (with); to have dealings (with)"
  },
  "交淺言深": {
    "pinyin": "jiao1 qian3 - yan2 shen1",
    "definition": "(idiom) to talk intimately while being comparative strangers"
  },
  "交火": {
    "pinyin": "jiao1 huo3",
    "definition": "firefight; shooting"
  },
  "交班": {
    "pinyin": "jiao1 ban1",
    "definition": "to hand over to the next workshift"
  },
  "交由": {
    "pinyin": "jiao1 you2",
    "definition": "to hand over (responsibility for sth) to (sb); to leave it to (sb else to take charge of the next stage of a process)"
  },
  "交界": {
    "pinyin": "jiao1 jie4",
    "definition": "common boundary; common border"
  },
  "交睫": {
    "pinyin": "jiao1 jie2",
    "definition": "to close one's eyes (i.e. sleep)"
  },
  "交管": {
    "pinyin": "jiao1 guan3",
    "definition": "traffic control"
  },
  "交管所": {
    "pinyin": "jiao1 guan3 suo3",
    "definition": "DMV (department of motor vehicles) (abbr. for 公安局交通管理局車輛管理所|公安局交通管理局车辆管理所)"
  },
  "交糧本": {
    "pinyin": "jiao1 liang2 ben3",
    "definition": "to hand in one's ration cards; to die"
  },
  "交納": {
    "pinyin": "jiao1 na4",
    "definition": "to pay (taxes or dues)"
  },
  "交結": {
    "pinyin": "jiao1 jie2",
    "definition": "to associate with; to mix with; to connect"
  },
  "交給": {
    "pinyin": "jiao1 gei3",
    "definition": "to give; to deliver; to hand over"
  },
  "交織": {
    "pinyin": "jiao1 zhi1",
    "definition": "to interweave"
  },
  "交纏": {
    "pinyin": "jiao1 chan2",
    "definition": "to intertwine; to intermingle"
  },
  "交臂": {
    "pinyin": "jiao1 bi4",
    "definition": "linking arms; arm in arm; very close"
  },
  "交臂失之": {
    "pinyin": "jiao1 bi4 shi1 zhi1",
    "definition": "to miss sb by a narrow chance; to miss an opportunity"
  },
  "交與": {
    "pinyin": "jiao1 yu3",
    "definition": "to hand over"
  },
  "交融": {
    "pinyin": "jiao1 rong2",
    "definition": "to blend; to mix"
  },
  "交規": {
    "pinyin": "jiao1 gui1",
    "definition": "traffic rules (abbr. for 交通規則|交通规则[jiao1 tong1 gui1 ze2])"
  },
  "交角": {
    "pinyin": "jiao1 jiao3",
    "definition": "(math.) angle of intersection"
  },
  "交誼": {
    "pinyin": "jiao1 yi4",
    "definition": "association; communion; friendship"
  },
  "交誼舞": {
    "pinyin": "jiao1 yi4 wu3",
    "definition": "social dance; ballroom dancing"
  },
  "交談": {
    "pinyin": "jiao1 tan2",
    "definition": "to discuss; to converse; chat; discussion"
  },
  "交警": {
    "pinyin": "jiao1 jing3",
    "definition": "traffic police (abbr. for 交通警察[jiao1tong1 jing3cha2])"
  },
  "交變": {
    "pinyin": "jiao1 bian4",
    "definition": "half-period of a wave motion; alternation"
  },
  "交變電流": {
    "pinyin": "jiao1 bian4 dian4 liu2",
    "definition": "alternating current (electricity)"
  },
  "交貨": {
    "pinyin": "jiao1 huo4",
    "definition": "to deliver goods"
  },
  "交貨期": {
    "pinyin": "jiao1 huo4 qi1",
    "definition": "delivery time (time between ordering goods and receiving the delivery); date of delivery"
  },
  "交費": {
    "pinyin": "jiao1 fei4",
    "definition": "to pay a fee"
  },
  "交趾": {
    "pinyin": "Jiao1 zhi3",
    "definition": "former southernmost province of the Chinese Empire, now northern Vietnam"
  },
  "交辦": {
    "pinyin": "jiao1 ban4",
    "definition": "to assign (a task to sb)"
  },
  "交迫": {
    "pinyin": "jiao1 po4",
    "definition": "to be beleaguered"
  },
  "交通": {
    "pinyin": "jiao1 tong1",
    "definition": "to be connected; traffic; transportation; communications; liaison"
  },
  "交通協管員": {
    "pinyin": "jiao1 tong1 xie2 guan3 yuan2",
    "definition": "traffic warden"
  },
  "交通卡": {
    "pinyin": "jiao1 tong1 ka3",
    "definition": "public transportation card; prepaid transit card; subway pass"
  },
  "交通堵塞": {
    "pinyin": "jiao1 tong1 du3 se4",
    "definition": "road congestion; traffic jam"
  },
  "交通大學": {
    "pinyin": "Jiao1 tong1 Da4 xue2",
    "definition": "abbr. for 上海交通大學|上海交通大学 Shanghai Jiao Tong University, 西安交通大學|西安交通大学 Xia'an Jiaotong University, 國立交通大學|国立交通大学 National Chiao Tung University (Taiwan) etc"
  },
  "交通工具": {
    "pinyin": "jiao1 tong1 gong1 ju4",
    "definition": "means of transportation; vehicle"
  },
  "交通意外": {
    "pinyin": "jiao1 tong1 yi4 wai4",
    "definition": "traffic accident; car crash"
  },
  "交通擁擠": {
    "pinyin": "jiao1 tong1 yong1 ji3",
    "definition": "traffic congestion"
  },
  "交通標誌": {
    "pinyin": "jiao1 tong1 biao1 zhi4",
    "definition": "traffic sign"
  },
  "交通樞紐": {
    "pinyin": "jiao1 tong1 shu1 niu3",
    "definition": "traffic hub"
  },
  "交通燈": {
    "pinyin": "jiao1 tong1 deng1",
    "definition": "traffic light"
  },
  "交通立體化": {
    "pinyin": "jiao1 tong1 li4 ti3 hua4",
    "definition": "grade separation (civil engineering)"
  },
  "交通管理局": {
    "pinyin": "jiao1 tong1 guan3 li3 ju2",
    "definition": "department of transport"
  },
  "交通肇事罪": {
    "pinyin": "jiao1 tong1 zhao4 shi4 zui4",
    "definition": "culpable driving causing serious damage or injury"
  },
  "交通規則": {
    "pinyin": "jiao1 tong1 gui1 ze2",
    "definition": "traffic rules; rules of the road"
  },
  "交通警察": {
    "pinyin": "jiao1 tong1 jing3 cha2",
    "definition": "traffic police"
  },
  "交通警衛": {
    "pinyin": "jiao1 tong1 jing3 wei4",
    "definition": "road traffic policing"
  },
  "交通費": {
    "pinyin": "jiao1 tong1 fei4",
    "definition": "transport costs"
  },
  "交通車": {
    "pinyin": "jiao1 tong1 che1",
    "definition": "shuttle bus"
  },
  "交通運輸部": {
    "pinyin": "Jiao1 tong1 Yun4 shu1 bu4",
    "definition": "PRC Ministry of Transport (MOT)"
  },
  "交通部": {
    "pinyin": "Jiao1 tong1 bu4",
    "definition": "Department of Transportation; (PRC) Ministry of Transport"
  },
  "交通銀行": {
    "pinyin": "Jiao1 tong1 Yin2 hang2",
    "definition": "Bank of Communications"
  },
  "交通錐": {
    "pinyin": "jiao1 tong1 zhui1",
    "definition": "traffic cone; road cone"
  },
  "交通阻塞": {
    "pinyin": "jiao1 tong1 zu3 se4",
    "definition": "traffic jam"
  },
  "交遊": {
    "pinyin": "jiao1 you2",
    "definition": "to have friendly relationships; circle of friends"
  },
  "交運": {
    "pinyin": "jiao1 yun4",
    "definition": "to meet with luck; to hand over for transportation; to check (one's baggage at an airport etc)"
  },
  "交還": {
    "pinyin": "jiao1 huan2",
    "definition": "to return sth; to hand back"
  },
  "交配": {
    "pinyin": "jiao1 pei4",
    "definition": "mating; copulation (esp. of animals)"
  },
  "交鋒": {
    "pinyin": "jiao1 feng1",
    "definition": "to cross swords; to have a confrontation (with sb)"
  },
  "交錢": {
    "pinyin": "jiao1 qian2",
    "definition": "to pay up; to shell out; to hand over the money to cover sth"
  },
  "交錯": {
    "pinyin": "jiao1 cuo4",
    "definition": "to crisscross; to intertwine"
  },
  "交際": {
    "pinyin": "jiao1 ji4",
    "definition": "communication; social intercourse"
  },
  "交際舞": {
    "pinyin": "jiao1 ji4 wu3",
    "definition": "social dance; ballroom dance"
  },
  "交際花": {
    "pinyin": "jiao1 ji4 hua1",
    "definition": "(female) social butterfly; socialite; courtesan"
  },
  "交集": {
    "pinyin": "jiao1 ji2",
    "definition": "(of diverse emotions) to occur simultaneously; to intermingle; common ground; points of commonality; overlap; connection; interaction; dealings; (math.) (set theory) intersection"
  },
  "交響": {
    "pinyin": "jiao1 xiang3",
    "definition": "symphony, symphonic"
  },
  "交響曲": {
    "pinyin": "jiao1 xiang3 qu3",
    "definition": "symphony"
  },
  "交響樂": {
    "pinyin": "jiao1 xiang3 yue4",
    "definition": "symphony"
  },
  "交響樂團": {
    "pinyin": "jiao1 xiang3 yue4 tuan2",
    "definition": "symphony orchestra"
  },
  "交響樂隊": {
    "pinyin": "jiao1 xiang3 yue4 dui4",
    "definition": "symphony orchestra"
  },
  "交響金屬": {
    "pinyin": "jiao1 xiang3 jin1 shu3",
    "definition": "symphonic metal (pop music); heavy metal with symphonic pretensions"
  },
  "交頭接耳": {
    "pinyin": "jiao1 tou2 jie1 er3",
    "definition": "to whisper to one another's ear"
  },
  "交馳": {
    "pinyin": "jiao1 chi2",
    "definition": "continuously circling one another; to buzz around"
  },
  "交骨": {
    "pinyin": "jiao1 gu3",
    "definition": "pubic bone"
  },
  "交點": {
    "pinyin": "jiao1 dian3",
    "definition": "meeting point; point of intersection"
  }
}