{
  "兀": {
    "pinyin": "wu4",
    "definition": "cut off the feet; rising to a height; towering; bald"
  },
  "兀凳": {
    "pinyin": "wu4 deng4",
    "definition": "Chinese-style low stool"
  },
  "兀立": {
    "pinyin": "wu4 li4",
    "definition": "to stand upright and motionless"
  },
  "兀自": {
    "pinyin": "wu4 zi4",
    "definition": "(literary) still; yet"
  },
  "兀臬": {
    "pinyin": "wu4 nie4",
    "definition": "variant of 杌隉|杌陧[wu4nie4]"
  },
  "兀臲": {
    "pinyin": "wu4 nie4",
    "definition": "variant of 杌隉|杌陧[wu4nie4]"
  },
  "兀鷲": {
    "pinyin": "wu4 jiu4",
    "definition": "vulture; (bird species of China) Eurasian griffon vulture (Gyps fulvus)"
  },
  "兀鷹": {
    "pinyin": "wu4 ying1",
    "definition": "bald eagle"
  }
}