{
  "則": {
    "pinyin": "zé",
    "definition": "(literary) (conjunction used to express contrast with a previous clause) but; then; (bound form) standard; norm; (bound form) principle; (literary) to imitate; to follow; classifier for written items"
  },
  "則個": {
    "pinyin": "zé gè",
    "definition": "(old sentence-final expression used for emphasis)"
  },
  "則步隆": {
    "pinyin": "zé bù lóng",
    "definition": "Zabulon or Zebulun, biblical land between Jordan and Galilee (Matthew 4:15)"
  },
  "則辣黑": {
    "pinyin": "zé là hēi",
    "definition": "Zerah (son of Judah in the Old Testament)"
  }
}