{
  "塘": {
    "pinyin": "tang2",
    "definition": "dyke; embankment; pool or pond; hot-water bathing pool"
  },
  "塘堰": {
    "pinyin": "tang2 yan4",
    "definition": "irrigation pond or dam"
  },
  "塘沽": {
    "pinyin": "Tang2 gu1",
    "definition": "Tanggu former district of Tianjin, now part of Binhai subprovincial district 濱海新區|滨海新区[Bin1 hai3 xin1 qu1]"
  },
  "塘沽區": {
    "pinyin": "Tang2 gu1 qu1",
    "definition": "Tanggu former district of Tianjin, now part of Binhai subprovincial district 濱海新區|滨海新区[Bin1 hai3 xin1 qu1]"
  },
  "塘虱": {
    "pinyin": "tang2 shi1",
    "definition": "catfish (family Clariidae)"
  },
  "塘角魚": {
    "pinyin": "tang2 jiao3 yu2",
    "definition": "Hong Kong catfish (Clarias fuscus)"
  },
  "塘鵝": {
    "pinyin": "tang2 e2",
    "definition": "pelican (Morus bassanus); gannet; booby"
  }
}