{
  "揭": {
    "pinyin": "jie1",
    "definition": "to take the lid off; to expose; to unmask"
  },
  "揭不開鍋": {
    "pinyin": "jie1 bu4 kai1 guo1",
    "definition": "to be unable to afford food"
  },
  "揭密": {
    "pinyin": "jie1 mi4",
    "definition": "variant of 揭秘[jie1mi4]"
  },
  "揭幕": {
    "pinyin": "jie1 mu4",
    "definition": "opening; unveiling"
  },
  "揭幕式": {
    "pinyin": "jie1 mu4 shi4",
    "definition": "opening ceremony; unveiling"
  },
  "揭底": {
    "pinyin": "jie1 di3",
    "definition": "to reveal the inside story; to expose sb's secrets"
  },
  "揭批": {
    "pinyin": "jie1 pi1",
    "definition": "to expose and criticize"
  },
  "揭曉": {
    "pinyin": "jie1 xiao3",
    "definition": "to announce publicly; to publish; to make known; to disclose"
  },
  "揭櫫": {
    "pinyin": "jie1 zhu1",
    "definition": "to disclose; to announce"
  },
  "揭牌": {
    "pinyin": "jie1 pai2",
    "definition": "to unveil the plaque for (a school, shop, stadium etc); to inaugurate; to officially open"
  },
  "揭發": {
    "pinyin": "jie1 fa1",
    "definition": "to expose; to bring to light; to disclose; revelation"
  },
  "揭短": {
    "pinyin": "jie1 duan3",
    "definition": "to expose sb's faults or shortcomings"
  },
  "揭破": {
    "pinyin": "jie1 po4",
    "definition": "to uncover"
  },
  "揭示": {
    "pinyin": "jie1 shi4",
    "definition": "to show; to make known"
  },
  "揭秘": {
    "pinyin": "jie1 mi4",
    "definition": "to reveal a secret"
  },
  "揭穿": {
    "pinyin": "jie1 chuan1",
    "definition": "to expose; to uncover"
  },
  "揭舉": {
    "pinyin": "jie1 ju3",
    "definition": "to lift up; (fig.) to put on display; to set forth; to expound"
  },
  "揭西": {
    "pinyin": "Jie1 xi1",
    "definition": "Jiexi county in Jieyang 揭陽|揭阳, Guangdong"
  },
  "揭西縣": {
    "pinyin": "Jie1 xi1 xian4",
    "definition": "Jiexi county in Jieyang 揭陽|揭阳, Guangdong"
  },
  "揭諦": {
    "pinyin": "jie1 di4",
    "definition": "revealer (protective god)"
  },
  "揭載": {
    "pinyin": "jie1 zai3",
    "definition": "to publish"
  },
  "揭開": {
    "pinyin": "jie1 kai1",
    "definition": "to uncover; to open"
  },
  "揭陽": {
    "pinyin": "Jie1 yang2",
    "definition": "see 揭陽市|揭阳市[Jie1yang2 Shi4]"
  },
  "揭陽市": {
    "pinyin": "Jie1 yang2 Shi4",
    "definition": "Jieyang, prefecture-level city in Guangdong Province 廣東省|广东省[Guang3dong1 Sheng3]"
  },
  "揭露": {
    "pinyin": "jie1 lu4",
    "definition": "to expose; to unmask; to ferret out; to disclose; disclosure"
  },
  "揭黑": {
    "pinyin": "jie1 hei1",
    "definition": "to uncover (mistakes, corruption etc); whistle-blowing"
  }
}