{
  "敬": {
    "pinyin": "jing4",
    "definition": "(bound form) respectful; to respect; to offer politely"
  },
  "敬上": {
    "pinyin": "jing4 shang4",
    "definition": "yours truly; yours sincerely (at the end of a letter)"
  },
  "敬仰": {
    "pinyin": "jing4 yang3",
    "definition": "to revere; highly esteemed"
  },
  "敬佩": {
    "pinyin": "jing4 pei4",
    "definition": "to esteem; to admire"
  },
  "敬備": {
    "pinyin": "jing4 bei4",
    "definition": "to respectfully offer"
  },
  "敬告": {
    "pinyin": "jing4 gao4",
    "definition": "to tell respectfully; to announce reverentially"
  },
  "敬啟": {
    "pinyin": "jing4 qi3",
    "definition": "respectful closing to a letter"
  },
  "敬啟者": {
    "pinyin": "jing4 qi3 zhe3",
    "definition": "Dear Sirs; To Whom It May Concern"
  },
  "敬奉": {
    "pinyin": "jing4 feng4",
    "definition": "to worship piously; to present; to dedicate"
  },
  "敬悉": {
    "pinyin": "jing4 xi1",
    "definition": "(honorific) revered news; the most valuable information (in your recent letter, book etc); Thank you for your letter."
  },
  "敬惜字紙": {
    "pinyin": "jing4 xi1 zi4 zhi3",
    "definition": "to treasure written material as a cultural resource (idiom)"
  },
  "敬意": {
    "pinyin": "jing4 yi4",
    "definition": "respect; esteem; high regard"
  },
  "敬愛": {
    "pinyin": "jing4 ai4",
    "definition": "to respect and love; to hold in high esteem"
  },
  "敬拜": {
    "pinyin": "jing4 bai4",
    "definition": "to worship"
  },
  "敬服": {
    "pinyin": "jing4 fu2",
    "definition": "deference; esteem; to admire"
  },
  "敬業": {
    "pinyin": "jing4 ye4",
    "definition": "dedicated to one's work"
  },
  "敬業樂群": {
    "pinyin": "jing4 ye4 le4 qun2",
    "definition": "diligent and sociable (idiom); meticulous in work and dealing cheerfully with one's colleagues"
  },
  "敬煙": {
    "pinyin": "jing4 yan1",
    "definition": "to offer a cigarette (to a guest)"
  },
  "敬畏": {
    "pinyin": "jing4 wei4",
    "definition": "to revere"
  },
  "敬祝": {
    "pinyin": "jing4 zhu4",
    "definition": "to offer humbly (written at the end of letter to sb of higher status); your humble servant"
  },
  "敬神": {
    "pinyin": "jing4 shen2",
    "definition": "to respect a deity; to pray to a God"
  },
  "敬禮": {
    "pinyin": "jing4 li3",
    "definition": "to salute; salute"
  },
  "敬稱": {
    "pinyin": "jing4 cheng1",
    "definition": "to address or refer to (sb) respectfully (as ...); respectful term of address; honorific title"
  },
  "敬老": {
    "pinyin": "jing4 lao3",
    "definition": "to respect the elderly"
  },
  "敬老尊賢": {
    "pinyin": "jing4 lao3 zun1 xian2",
    "definition": "to respect the wise and venerate the worthy (idiom); to honor the great and the good"
  },
  "敬老席": {
    "pinyin": "jing4 lao3 xi2",
    "definition": "priority seating for the aged (on buses etc)"
  },
  "敬老院": {
    "pinyin": "jing4 lao3 yuan4",
    "definition": "senior citizens' home; old folks' home"
  },
  "敬而遠之": {
    "pinyin": "jing4 er2 yuan3 zhi1",
    "definition": "to show respect from a distance (idiom); to remain at a respectful distance"
  },
  "敬若神明": {
    "pinyin": "jing4 ruo4 shen2 ming2",
    "definition": "to hold sb in the same regard as one would a god (idiom)"
  },
  "敬茶": {
    "pinyin": "jing4 cha2",
    "definition": "to serve tea (to guests)"
  },
  "敬虔": {
    "pinyin": "jing4 qian2",
    "definition": "devout"
  },
  "敬詞": {
    "pinyin": "jing4 ci2",
    "definition": "term of respect; polite expression"
  },
  "敬語": {
    "pinyin": "jing4 yu3",
    "definition": "honorific (e.g. in grammar of oriental languages)"
  },
  "敬請": {
    "pinyin": "jing4 qing3",
    "definition": "please (do sth) (deferential form)"
  },
  "敬謝不敏": {
    "pinyin": "jing4 xie4 bu4 min3",
    "definition": "please excuse me for not complying; to politely decline"
  },
  "敬賀": {
    "pinyin": "jing4 he4",
    "definition": "to offer one's congratulations (formal)"
  },
  "敬賢禮士": {
    "pinyin": "jing4 xian2 - li3 shi4",
    "definition": "(idiom) to respect people of virtue and show courtesy to scholars"
  },
  "敬贈": {
    "pinyin": "jing4 zeng4",
    "definition": "to present respectfully; with (sb's) compliments; complimentary"
  },
  "敬辭": {
    "pinyin": "jing4 ci2",
    "definition": "term of respect; polite expression"
  },
  "敬酒": {
    "pinyin": "jing4 jiu3",
    "definition": "to toast; to propose a toast"
  },
  "敬酒不吃吃罰酒": {
    "pinyin": "jing4 jiu3 bu4 chi1 chi1 fa2 jiu3",
    "definition": "lit. to refuse a toast only to be forced to drink a forfeit (idiom); fig. to turn down a request only to be forced later to comply with it under pressure"
  },
  "敬重": {
    "pinyin": "jing4 zhong4",
    "definition": "to respect deeply; to revere; to esteem"
  },
  "敬鬼神而遠之": {
    "pinyin": "jing4 gui3 shen2 er2 yuan3 zhi1",
    "definition": "to respect Gods and demons from a distance (idiom); to remain at a respectful distance"
  }
}