{
  "斂": {
    "pinyin": "lian4",
    "definition": "variant of 殮|殓[lian4]"
  },
  "斂巴": {
    "pinyin": "lian3 ba5",
    "definition": "(dialect) to gather up; to throw together"
  },
  "斂步": {
    "pinyin": "lian3 bu4",
    "definition": "(literary) to slow down one's steps; to come to a halt"
  },
  "斂衽": {
    "pinyin": "lian3 ren4",
    "definition": "old-fashioned women's obeisance; Taiwan pr. [lian4 ren4]"
  },
  "斂財": {
    "pinyin": "lian3 cai2",
    "definition": "to accumulate wealth; to rake in money"
  },
  "斂跡": {
    "pinyin": "lian3 ji4",
    "definition": "to refrain; to give up evil (temporarily); to cover one's traces; to lie low; to retire (from view)"
  },
  "斂錢": {
    "pinyin": "lian3 qian2",
    "definition": "to collect money; to raise funds (for charity)"
  }
}