{
  "瓷": {
    "pinyin": "ci2",
    "definition": "chinaware; porcelain; china"
  },
  "瓷器": {
    "pinyin": "ci2 qi4",
    "definition": "chinaware; porcelain"
  },
  "瓷實": {
    "pinyin": "ci2 shi5",
    "definition": "(dialect) firm; robust"
  },
  "瓷瓶": {
    "pinyin": "ci2 ping2",
    "definition": "porcelain bottle"
  },
  "瓷碗": {
    "pinyin": "ci2 wan3",
    "definition": "porcelain bowl"
  },
  "瓷磚": {
    "pinyin": "ci2 zhuan1",
    "definition": "ceramic tile"
  },
  "瓷釉": {
    "pinyin": "ci2 you4",
    "definition": "porcelain glaze"
  }
}