{
  "砲": {
    "pinyin": "pao4",
    "definition": "variant of 炮[pao4]"
  },
  "砲手": {
    "pinyin": "pao4 shou3",
    "definition": "gunner; artillery crew"
  },
  "砲擊": {
    "pinyin": "pao4 ji1",
    "definition": "to shell; to bombard; bombardment"
  },
  "砲火連天": {
    "pinyin": "pao4 huo3 lian2 tian1",
    "definition": "cannon firing for days on end (idiom); enveloped in the flames of war"
  },
  "砲臺": {
    "pinyin": "pao4 tai2",
    "definition": "fort; battery"
  },
  "砲艇": {
    "pinyin": "pao4 ting3",
    "definition": "gunboat"
  },
  "砲艦": {
    "pinyin": "pao4 jian4",
    "definition": "gunboat; gunship"
  },
  "砲轟": {
    "pinyin": "pao4 hong1",
    "definition": "variant of 炮轟|炮轰[pao4 hong1]"
  },
  "砲響": {
    "pinyin": "pao4 xiang3",
    "definition": "sound of gunfire; fig. news of momentous events"
  }
}