{
  "篤": {
    "pinyin": "dǔ",
    "definition": "serious (illness); sincere; true"
  },
  "篤信": {
    "pinyin": "dǔ xìn",
    "definition": "to sincerely believe"
  },
  "篤信好學": {
    "pinyin": "dǔ xìn hǎo xué",
    "definition": "sincere belief and diligent study"
  },
  "篤厚": {
    "pinyin": "dǔ hòu",
    "definition": "honest and generous; magnanimous"
  },
  "篤學": {
    "pinyin": "dǔ xué",
    "definition": "studious; diligent in study"
  },
  "篤守": {
    "pinyin": "dǔ shǒu",
    "definition": "to comply faithfully; sincerely abiding by"
  },
  "篤定": {
    "pinyin": "dǔ dìng",
    "definition": "certain; confident (of some outcome); calm and unhurried"
  },
  "篤實": {
    "pinyin": "dǔ shí",
    "definition": "loyal; sincere; sound"
  },
  "篤專": {
    "pinyin": "dǔ zhuān",
    "definition": "with undivided attention"
  },
  "篤志": {
    "pinyin": "dǔ zhì",
    "definition": "steadfast; with single-minded devotion"
  },
  "篤愛": {
    "pinyin": "dǔ ài",
    "definition": "to love deeply; devoted to sb"
  },
  "篤摯": {
    "pinyin": "dǔ zhì",
    "definition": "sincere (in friendship); cordial"
  },
  "篤病": {
    "pinyin": "dǔ bìng",
    "definition": "seriously ill; critical"
  },
  "篤行": {
    "pinyin": "dǔ xíng",
    "definition": "to carry out (obligation) conscientiously; to behave sincerely"
  }
}