{
  "篤": {
    "pinyin": "du3",
    "definition": "serious (illness); sincere; true"
  },
  "篤信": {
    "pinyin": "du3 xin4",
    "definition": "to sincerely believe"
  },
  "篤信好學": {
    "pinyin": "du3 xin4 hao4 xue2",
    "definition": "sincere belief and diligent study"
  },
  "篤厚": {
    "pinyin": "du3 hou4",
    "definition": "honest and generous; magnanimous"
  },
  "篤學": {
    "pinyin": "du3 xue2",
    "definition": "studious; diligent in study"
  },
  "篤守": {
    "pinyin": "du3 shou3",
    "definition": "to comply faithfully; sincerely abiding by"
  },
  "篤定": {
    "pinyin": "du3 ding4",
    "definition": "certain; confident (of some outcome); calm and unhurried"
  },
  "篤實": {
    "pinyin": "du3 shi2",
    "definition": "loyal; sincere; sound"
  },
  "篤專": {
    "pinyin": "du3 zhuan1",
    "definition": "with undivided attention"
  },
  "篤志": {
    "pinyin": "du3 zhi4",
    "definition": "steadfast; with single-minded devotion"
  },
  "篤愛": {
    "pinyin": "du3 ai4",
    "definition": "to love deeply; devoted to sb"
  },
  "篤摯": {
    "pinyin": "du3 zhi4",
    "definition": "sincere (in friendship); cordial"
  },
  "篤病": {
    "pinyin": "du3 bing4",
    "definition": "seriously ill; critical"
  },
  "篤行": {
    "pinyin": "du3 xing2",
    "definition": "to carry out (obligation) conscientiously; to behave sincerely"
  }
}