{
  "脖": {
    "pinyin": "bó",
    "definition": "neck"
  },
  "脖子": {
    "pinyin": "bó zi",
    "definition": "neck; CL:個|个[ge4]"
  },
  "脖梗": {
    "pinyin": "bó gěng",
    "definition": "variant of 脖頸|脖颈[bo2geng3]"
  },
  "脖梗兒": {
    "pinyin": "bó gěng ér",
    "definition": "erhua variant of 脖梗[bo2geng3]"
  },
  "脖梗子": {
    "pinyin": "bó gěng zi",
    "definition": "variant of 脖頸子|脖颈子[bo2geng3zi5]"
  },
  "脖領": {
    "pinyin": "bó lǐng",
    "definition": "shirt collar"
  },
  "脖頸": {
    "pinyin": "bó jǐng",
    "definition": "back of the neck; nape"
  },
  "脖頸兒": {
    "pinyin": "bó jǐng ér",
    "definition": "erhua variant of 脖頸|脖颈[bo2geng3]"
  },
  "脖頸子": {
    "pinyin": "bó jǐng zi",
    "definition": "see 脖頸|脖颈[bo2geng3]"
  }
}