{
  "舟": {
    "pinyin": "zhou1",
    "definition": "boat"
  },
  "舟山": {
    "pinyin": "Zhou1 shan1",
    "definition": "see 舟山市[Zhou1shan1 Shi4]"
  },
  "舟山市": {
    "pinyin": "Zhou1 shan1 Shi4",
    "definition": "Zhoushan, prefecture-level city in Zhejiang Province 浙江省[Zhe4jiang1 Sheng3]"
  },
  "舟山群島": {
    "pinyin": "Zhou1 shan1 Qun2 dao3",
    "definition": "Zhoushan Island"
  },
  "舟曲": {
    "pinyin": "Zhou1 qu3",
    "definition": "Zhugqu or Zhouqu County in Gannan Tibetan Autonomous Prefecture 甘南藏族自治州[Gan1 nan2 Zang4 zu2 Zi4 zhi4 zhou1], Gansu"
  },
  "舟曲縣": {
    "pinyin": "Zhou1 qu3 Xian4",
    "definition": "Zhugqu or Zhouqu County in Gannan Tibetan Autonomous Prefecture 甘南藏族自治州[Gan1 nan2 Zang4 zu2 Zi4 zhi4 zhou1], Gansu"
  },
  "舟船": {
    "pinyin": "zhou1 chuan2",
    "definition": "boat"
  },
  "舟車勞頓": {
    "pinyin": "zhou1 che1 lao2 dun4",
    "definition": "travel-worn"
  }
}