{
  "芙": {
    "pinyin": "fú",
    "definition": "used in 芙蓉[fu2 rong2], lotus"
  },
  "芙蓉": {
    "pinyin": "fú róng",
    "definition": "cotton rose hibiscus (Hibiscus mutabilis); lotus; foo yung (Chinese dish similar to an omelet)"
  },
  "芙蓉出水": {
    "pinyin": "fú róng chū shuǐ",
    "definition": "lit. lotus rises from the water (idiom); fig. to blossom (of poem or art)"
  },
  "芙蓉區": {
    "pinyin": "fú róng qū",
    "definition": "Furong district of Changsha city 長沙市|长沙市[Chang2 sha1 shi4], Hunan"
  },
  "芙蓉花": {
    "pinyin": "fú róng huā",
    "definition": "cotton rose hibiscus (Hibiscus mutabilis); lotus"
  }
}