{
  "隆": {
    "pinyin": "lóng",
    "definition": "grand; intense; prosperous; to swell; to bulge"
  },
  "隆中": {
    "pinyin": "lóng zhōng",
    "definition": "scenic area near Xiangyang 襄陽|襄阳[Xiang1 yang2] in Hubei, known as the secluded mountainous location where Zhuge Liang 諸葛亮|诸葛亮[Zhu1 ge3 Liang4] lived as a young man"
  },
  "隆乳": {
    "pinyin": "lóng rǔ",
    "definition": "breast enlargement"
  },
  "隆乳手術": {
    "pinyin": "lóng rǔ shǒu shù",
    "definition": "breast enlargement operation; boob job"
  },
  "隆冬": {
    "pinyin": "lóng dōng",
    "definition": "midwinter; the depth of winter"
  },
  "隆化": {
    "pinyin": "lóng huà",
    "definition": "Longhua county in Chengde 承德[Cheng2 de2], Hebei"
  },
  "隆化縣": {
    "pinyin": "lóng huà xiàn",
    "definition": "Longhua county in Chengde 承德[Cheng2 de2], Hebei"
  },
  "隆回": {
    "pinyin": "lóng huí",
    "definition": "Longhui county in Shaoyang 邵陽|邵阳[Shao4 yang2], Hunan"
  },
  "隆回縣": {
    "pinyin": "lóng huí xiàn",
    "definition": "Longhui county in Shaoyang 邵陽|邵阳[Shao4 yang2], Hunan"
  },
  "隆堯": {
    "pinyin": "lóng yáo",
    "definition": "Longyao county in Xingtai 邢台[Xing2 tai2], Hebei"
  },
  "隆堯縣": {
    "pinyin": "lóng yáo xiàn",
    "definition": "Longyao county in Xingtai 邢台[Xing2 tai2], Hebei"
  },
  "隆安": {
    "pinyin": "lóng ān",
    "definition": "Long'an county in Nanning 南寧|南宁[Nan2 ning2], Guangxi"
  },
  "隆安縣": {
    "pinyin": "lóng ān xiàn",
    "definition": "Long'an county in Nanning 南寧|南宁[Nan2 ning2], Guangxi"
  },
  "隆德": {
    "pinyin": "lóng dé",
    "definition": "Longde county in Guyuan 固原[Gu4 yuan2], Ningxia"
  },
  "隆德縣": {
    "pinyin": "lóng dé xiàn",
    "definition": "Longde county in Guyuan 固原[Gu4 yuan2], Ningxia"
  },
  "隆情": {
    "pinyin": "lóng qíng",
    "definition": "profound love"
  },
  "隆情厚誼": {
    "pinyin": "lóng qíng hòu yì",
    "definition": "profound love, generous friendship (idiom)"
  },
  "隆林各族自治縣": {
    "pinyin": "lóng lín gè zú zì zhì xiàn",
    "definition": "Longlin Various Nationalities Autonomous County in Baise 百色[Bai3 se4], Guangxi"
  },
  "隆林縣": {
    "pinyin": "lóng lín xiàn",
    "definition": "Longlin various ethnic groups autonomous county in Baise 百色[Bai3 se4], Guangxi"
  },
  "隆格爾": {
    "pinyin": "lóng gé ěr",
    "definition": "former Lunggar county 1983-1999 occupying parts of Zhongba county 仲巴縣|仲巴县[Zhong4 ba1 xian4], Ngari prefecture, Tibet"
  },
  "隆格爾縣": {
    "pinyin": "lóng gé ěr xiàn",
    "definition": "former Lunggar county 1983-1999 occupying parts of Zhongba county 仲巴縣|仲巴县[Zhong4 ba1 xian4], Ngari prefecture, Tibet"
  },
  "隆河": {
    "pinyin": "lóng hé",
    "definition": "Rhone, river of Switzerland and France; also written 羅納河|罗纳河[Luo2 na4 He2]"
  },
  "隆胸": {
    "pinyin": "lóng xiōng",
    "definition": "to enlarge the breasts; breast enlargement"
  },
  "隆起": {
    "pinyin": "lóng qǐ",
    "definition": "to swell; to bulge"
  },
  "隆重": {
    "pinyin": "lóng zhòng",
    "definition": "grand; prosperous; ceremonious; solemn"
  },
  "隆陽": {
    "pinyin": "lóng yáng",
    "definition": "Longyang district of Baoshan city 保山市[Bao3 shan1 shi4], Yunnan"
  },
  "隆陽區": {
    "pinyin": "lóng yáng qū",
    "definition": "Longyang district of Baoshan city 保山市[Bao3 shan1 shi4], Yunnan"
  },
  "隆隆": {
    "pinyin": "lóng lóng",
    "definition": "rumble"
  },
  "隆隆聲": {
    "pinyin": "lóng lóng shēng",
    "definition": "rumble (sound of thunder or gunfire)"
  }
}